Metadata-Version: 2.1
Name: geoindia
Version: 0.0.1
Summary: A python package for interactive mapping.
Home-page: https://github.com/doke93/geoindia
Author: Abhishek Doke
Author-email: dokeabhishek3@gmail.com
License: MIT license
Keywords: geoindia
Classifier: Development Status :: 2 - Pre-Alpha
Classifier: Intended Audience :: Developers
Classifier: License :: OSI Approved :: MIT License
Classifier: Natural Language :: English
Classifier: Programming Language :: Python :: 3
Classifier: Programming Language :: Python :: 3.7
Classifier: Programming Language :: Python :: 3.8
Classifier: Programming Language :: Python :: 3.9
Classifier: Programming Language :: Python :: 3.10
Requires-Python: >=3.7
License-File: LICENSE
